README.md
pyproject.toml
setup.cfg
setup.py
spacetower_cdm_recomputation_python_client/__init__.py
spacetower_cdm_recomputation_python_client/api_client.py
spacetower_cdm_recomputation_python_client/api_response.py
spacetower_cdm_recomputation_python_client/configuration.py
spacetower_cdm_recomputation_python_client/exceptions.py
spacetower_cdm_recomputation_python_client/py.typed
spacetower_cdm_recomputation_python_client/rest.py
spacetower_cdm_recomputation_python_client.egg-info/PKG-INFO
spacetower_cdm_recomputation_python_client.egg-info/SOURCES.txt
spacetower_cdm_recomputation_python_client.egg-info/dependency_links.txt
spacetower_cdm_recomputation_python_client.egg-info/requires.txt
spacetower_cdm_recomputation_python_client.egg-info/top_level.txt
spacetower_cdm_recomputation_python_client/api/__init__.py
spacetower_cdm_recomputation_python_client/api/default_api.py
spacetower_cdm_recomputation_python_client/models/__init__.py
test/test_default_api.py