Metadata-Version: 2.1
Name: spacetower_cdm_recomputation_python_client
Version: 0.1.1
Summary: CDM Recomputation API
Home-page: 
Author: OpenAPI Generator community
Author-email: team@openapitools.org
License: Exotrail
Keywords: OpenAPI,OpenAPI-Generator,CDM Recomputation API
Requires-Dist: urllib3<2.1.0,>=1.25.3
Requires-Dist: python-dateutil
Requires-Dist: pydantic>=2
Requires-Dist: typing-extensions>=4.7.1
